ghchain/__init__.py
ghchain/cli.py
ghchain/commit.py
ghchain/config.py
ghchain/git_utils.py
ghchain/github_utils.py
ghchain/handlers.py
ghchain/pull_request.py
ghchain/stack.py
ghchain/status.py
ghchain/utils.py
ghchain-0.1.8.dist-info/LICENSE
ghchain-0.1.8.dist-info/METADATA
ghchain-0.1.8.dist-info/WHEEL
ghchain-0.1.8.dist-info/entry_points.txt
ghchain-0.1.8.dist-info/top_level.txt
ghchain-0.1.8.dist-info/RECORD
