Metadata-Version: 2.2
Name: ghchain
Version: 0.1.8
Summary: Chain pull requests from your devbranch's commits.
Author-email: Hendrik Klug <hendrik.klug@gmail.com>
License: MIT license
Project-URL: Homepage, https://github.com/Jimmy2027/ghchain
Keywords: ghchain
Classifier: License :: OSI Approved :: MIT License
Classifier: Natural Language :: English
Classifier: Programming Language :: Python :: 3
Classifier: Programming Language :: Python :: 3.9
Classifier: Programming Language :: Python :: 3.10
Classifier: Programming Language :: Python :: 3.11
Classifier: Programming Language :: Python :: 3.12
Classifier: Programming Language :: Python :: 3.13
Requires-Python: >=3.9
License-File: LICENSE
Requires-Dist: Click>=7.0
Requires-Dist: rich
Requires-Dist: loguru
Requires-Dist: pydantic>2
Requires-Dist: GitPython
Requires-Dist: pandas
Requires-Dist: tabulate
